promptplex/__init__.py
promptplex/core.py
tests/__init__.py
tests/test_promptplex.py
promptplex-0.1.0.dist-info/METADATA
promptplex-0.1.0.dist-info/WHEEL
promptplex-0.1.0.dist-info/top_level.txt
promptplex-0.1.0.dist-info/RECORD
