Metadata-Version: 2.4
Name: promptplex
Version: 0.1.0
Summary: A Python library for mastering AI prompts with versioning, templating, and testing
Home-page: https://github.com/ejigsonpeter/promptplex
Author: Ejiga Peter Ojonugwa Oluwafemi
Author-email: Ejiga Peter Ojonugwa Oluwafemi <ejigsonpeter@gmail.com>
License: MIT
Project-URL: Homepage, https://github.com/ejigsonpeter/promptplex
Project-URL: Bug Reports, https://github.com/ejigsonpeter/promptplex/issues
Project-URL: Source, https://github.com/ejigsonpeter/promptplex
Keywords: ai,prompts,templates,llm,prompt-engineering
Classifier: Development Status :: 4 - Beta
Classifier: Intended Audience :: Developers
Classifier: License :: OSI Approved :: MIT License
Classifier: Operating System :: OS Independent
Classifier: Programming Language :: Python :: 3
Classifier: Programming Language :: Python :: 3.8
Classifier: Programming Language :: Python :: 3.9
Classifier: Programming Language :: Python :: 3.10
Classifier: Programming Language :: Python :: 3.11
Classifier: Programming Language :: Python :: 3.12
Classifier: Topic :: Software Development :: Libraries :: Python Modules
Classifier: Topic :: Scientific/Engineering :: Artificial Intelligence
Requires-Python: >=3.8
Requires-Dist: PyYAML>=6.0
Provides-Extra: dev
Requires-Dist: pytest>=7.0; extra == "dev"
Requires-Dist: black>=22.0; extra == "dev"
Requires-Dist: flake8>=4.0; extra == "dev"
Requires-Dist: mypy>=0.991; extra == "dev"
Provides-Extra: test
Requires-Dist: pytest>=7.0; extra == "test"
Requires-Dist: pytest-cov>=4.0; extra == "test"
Dynamic: author
Dynamic: home-page
Dynamic: requires-python
